{
  "pillars":{
    "fr":"Piliers",
    "en":"Pillars"
  },
  "programs":{
    "fr":"Programmes",
    "en":"Programs"
  },
  "topics":{
    "fr":"Thématiques",
    "en":"Topics"
  },
  "destinations":{
    "fr":"Destinations",
    "en":"Destinations"
  },
  "search":{
    "fr":"Rechercher",
    "en":"Search"
  },
  "reset":{
    "fr":"Réinitialiser",
    "en":"Reset"
  },
  "select":{
    "fr":"sélectionner tout",
    "en":"select all"
  },
  "unselect":{
    "fr":"désélectionner tout",
    "en":"unselect all"
  }
}